south_mysqlndb/__init__.py
south_mysqlndb/mysqlndb.py
south_mysqlndb-0.1.1.dist-info/DESCRIPTION.rst
south_mysqlndb-0.1.1.dist-info/METADATA
south_mysqlndb-0.1.1.dist-info/metadata.json
south_mysqlndb-0.1.1.dist-info/RECORD
south_mysqlndb-0.1.1.dist-info/top_level.txt
south_mysqlndb-0.1.1.dist-info/WHEEL
