Metadata-Version: 2.0
Name: south-mysqlndb
Version: 0.1.1
Summary: south database adapter for mysqlndb
Home-page: https://github.com/jimmykobe1171/south-mysqlndb
Author: Jimmy Cheung
Author-email: jimmykobe1171@126.com
License: MIT
Platform: UNKNOWN
